config/__init__.py
libretro_finder/__init__.py
libretro_finder/main.py
libretro_finder/utils.py
libretro_finder-0.3.1.dist-info/LICENSE
libretro_finder-0.3.1.dist-info/METADATA
libretro_finder-0.3.1.dist-info/WHEEL
libretro_finder-0.3.1.dist-info/entry_points.txt
libretro_finder-0.3.1.dist-info/RECORD
