Metadata-Version: 2.1
Name: libretro-finder
Version: 0.3.1
Summary: Simple tool that finds and prepares your BIOS files for usage with Libretro (or its RetroArch frontend).
Home-page: https://github.com/jaspersiebring/libretro_finder
License: GNU General Public License v3.0
Author: Jasper Siebring
Author-email: j.siebring92@gmail.com
Requires-Python: >=3.9,<3.13
Classifier: License :: Other/Proprietary License
Classifier: Programming Language :: Python :: 3
Classifier: Programming Language :: Python :: 3.9
Classifier: Programming Language :: Python :: 3.10
Classifier: Programming Language :: Python :: 3.11
Classifier: Programming Language :: Python :: 3.12
Requires-Dist: gooey (>=1.0.8.1,<2.0.0.0)
Requires-Dist: pandas (>=2.1.4,<3.0.0)
Requires-Dist: tqdm (>=4.66.1,<5.0.0)
Requires-Dist: vdf (>=3.4,<4.0)
Requires-Dist: wxpython (>=4.2.1,<5.0.0)
